[
  {
    "id": 1,
    "title": "女子穿着带有巨大吊牌旗袍街头拍照",
    "category": "社会",
    "source": "今日头条",
    "publishTime": "2026-05-16 05:17:21",
    "heat": 52201528,
    "trend": "rising",
    "sentiment": "neutral",
    "riskLevel": "medium",
    "isHot": true,
    "isNew": true,
    "excerpt": "",
    "keywords": [
      "女子穿着",
      "带有巨大",
      "女子穿着带有"
    ],
    "platform": "toutiao",
    "url": "https://www.toutiao.com/item//",
    "timeline": [
      {
        "time": "05:17",
        "title": "事件发现",
        "desc": "今日头条 监测到该热点",
        "isKey": true
      }
    ],
    "analysis": {
      "sentiment": "neutral",
      "sentimentScore": 0.65,
      "riskAssessment": "medium",
      "trendPrediction": "待观察",
      "keyPoints": [
        "事件正在发展中",
        "需持续关注官方通报",
        "建议跟踪后续报道"
      ]
    }
  },
  {
    "id": 2,
    "title": "英伟达给黄仁勋儿女涨薪了",
    "category": "社会",
    "source": "今日头条",
    "publishTime": "2026-05-16 05:17:21",
    "heat": 47233895,
    "trend": "rising",
    "sentiment": "neutral",
    "riskLevel": "medium",
    "isHot": true,
    "isNew": true,
    "excerpt": "",
    "keywords": [
      "英伟达给",
      "黄仁勋儿",
      "英伟达给黄仁"
    ],
    "platform": "toutiao",
    "url": "https://www.toutiao.com/item//",
    "timeline": [
      {
        "time": "05:17",
        "title": "事件发现",
        "desc": "今日头条 监测到该热点",
        "isKey": true
      }
    ],
    "analysis": {
      "sentiment": "neutral",
      "sentimentScore": 0.65,
      "riskAssessment": "medium",
      "trendPrediction": "待观察",
      "keyPoints": [
        "事件正在发展中",
        "需持续关注官方通报",
        "建议跟踪后续报道"
      ]
    }
  },
  {
    "id": 3,
    "title": "国产光纤光模块热卖全球",
    "category": "社会",
    "source": "今日头条",
    "publishTime": "2026-05-16 05:17:21",
    "heat": 42738996,
    "trend": "rising",
    "sentiment": "neutral",
    "riskLevel": "medium",
    "isHot": true,
    "isNew": true,
    "excerpt": "",
    "keywords": [
      "国产光纤",
      "光模块热",
      "国产光纤光模"
    ],
    "platform": "toutiao",
    "url": "https://www.toutiao.com/item//",
    "timeline": [
      {
        "time": "05:17",
        "title": "事件发现",
        "desc": "今日头条 监测到该热点",
        "isKey": true
      }
    ],
    "analysis": {
      "sentiment": "neutral",
      "sentimentScore": 0.65,
      "riskAssessment": "medium",
      "trendPrediction": "待观察",
      "keyPoints": [
        "事件正在发展中",
        "需持续关注官方通报",
        "建议跟踪后续报道"
      ]
    }
  },
  {
    "id": 4,
    "title": "台湾教师谈大陆人民为什么渴望统一",
    "category": "社会",
    "source": "今日头条",
    "publishTime": "2026-05-16 05:17:21",
    "heat": 38671843,
    "trend": "rising",
    "sentiment": "neutral",
    "riskLevel": "medium",
    "isHot": true,
    "isNew": true,
    "excerpt": "",
    "keywords": [
      "台湾教师",
      "谈大陆人",
      "台湾教师谈大"
    ],
    "platform": "toutiao",
    "url": "https://www.toutiao.com/item//",
    "timeline": [
      {
        "time": "05:17",
        "title": "事件发现",
        "desc": "今日头条 监测到该热点",
        "isKey": true
      }
    ],
    "analysis": {
      "sentiment": "neutral",
      "sentimentScore": 0.65,
      "riskAssessment": "medium",
      "trendPrediction": "待观察",
      "keyPoints": [
        "事件正在发展中",
        "需持续关注官方通报",
        "建议跟踪后续报道"
      ]
    }
  },
  {
    "id": 5,
    "title": "提车第1天开沟里 女子淡定合影",
    "category": "社会",
    "source": "今日头条",
    "publishTime": "2026-05-16 05:17:21",
    "heat": 34991730,
    "trend": "rising",
    "sentiment": "neutral",
    "riskLevel": "medium",
    "isHot": true,
    "isNew": true,
    "excerpt": "",
    "keywords": [
      "提车第1",
      "天开沟里",
      "提车第1天开"
    ],
    "platform": "toutiao",
    "url": "https://www.toutiao.com/item//",
    "timeline": [
      {
        "time": "05:17",
        "title": "事件发现",
        "desc": "今日头条 监测到该热点",
        "isKey": true
      }
    ],
    "analysis": {
      "sentiment": "neutral",
      "sentimentScore": 0.65,
      "riskAssessment": "medium",
      "trendPrediction": "待观察",
      "keyPoints": [
        "事件正在发展中",
        "需持续关注官方通报",
        "建议跟踪后续报道"
      ]
    }
  },
  {
    "id": 6,
    "title": "网警通报虚假摆拍盲人盲道被撞案",
    "category": "社会",
    "source": "今日头条",
    "publishTime": "2026-05-16 05:17:21",
    "heat": 31661827,
    "trend": "rising",
    "sentiment": "neutral",
    "riskLevel": "medium",
    "isHot": true,
    "isNew": true,
    "excerpt": "",
    "keywords": [
      "网警通报",
      "虚假摆拍",
      "网警通报虚假"
    ],
    "platform": "toutiao",
    "url": "https://www.toutiao.com/item//",
    "timeline": [
      {
        "time": "05:17",
        "title": "事件发现",
        "desc": "今日头条 监测到该热点",
        "isKey": true
      }
    ],
    "analysis": {
      "sentiment": "neutral",
      "sentimentScore": 0.65,
      "riskAssessment": "medium",
      "trendPrediction": "待观察",
      "keyPoints": [
        "事件正在发展中",
        "需持续关注官方通报",
        "建议跟踪后续报道"
      ]
    }
  },
  {
    "id": 7,
    "title": "金价大跌",
    "category": "社会",
    "source": "今日头条",
    "publishTime": "2026-05-16 05:17:21",
    "heat": 28648805,
    "trend": "rising",
    "sentiment": "neutral",
    "riskLevel": "medium",
    "isHot": true,
    "isNew": true,
    "excerpt": "",
    "keywords": [
      "金价大跌"
    ],
    "platform": "toutiao",
    "url": "https://www.toutiao.com/item//",
    "timeline": [
      {
        "time": "05:17",
        "title": "事件发现",
        "desc": "今日头条 监测到该热点",
        "isKey": true
      }
    ],
    "analysis": {
      "sentiment": "neutral",
      "sentimentScore": 0.65,
      "riskAssessment": "medium",
      "trendPrediction": "待观察",
      "keyPoints": [
        "事件正在发展中",
        "需持续关注官方通报",
        "建议跟踪后续报道"
      ]
    }
  },
  {
    "id": 8,
    "title": "30分大胜 马刺4-2淘汰森林狼晋级西决",
    "category": "社会",
    "source": "今日头条",
    "publishTime": "2026-05-16 05:17:21",
    "heat": 25922511,
    "trend": "rising",
    "sentiment": "neutral",
    "riskLevel": "medium",
    "isHot": true,
    "isNew": true,
    "excerpt": "",
    "keywords": [
      "30分大",
      "胜 马刺",
      "30分大胜 "
    ],
    "platform": "toutiao",
    "url": "https://www.toutiao.com/item//",
    "timeline": [
      {
        "time": "05:17",
        "title": "事件发现",
        "desc": "今日头条 监测到该热点",
        "isKey": true
      }
    ],
    "analysis": {
      "sentiment": "neutral",
      "sentimentScore": 0.65,
      "riskAssessment": "medium",
      "trendPrediction": "待观察",
      "keyPoints": [
        "事件正在发展中",
        "需持续关注官方通报",
        "建议跟踪后续报道"
      ]
    }
  },
  {
    "id": 9,
    "title": "洁丽雅家族被质疑“家族关系混乱”",
    "category": "社会",
    "source": "今日头条",
    "publishTime": "2026-05-16 05:17:21",
    "heat": 23455658,
    "trend": "rising",
    "sentiment": "neutral",
    "riskLevel": "medium",
    "isHot": true,
    "isNew": true,
    "excerpt": "",
    "keywords": [
      "洁丽雅家",
      "族被质疑",
      "洁丽雅家族被"
    ],
    "platform": "toutiao",
    "url": "https://www.toutiao.com/item//",
    "timeline": [
      {
        "time": "05:17",
        "title": "事件发现",
        "desc": "今日头条 监测到该热点",
        "isKey": true
      }
    ],
    "analysis": {
      "sentiment": "neutral",
      "sentimentScore": 0.65,
      "riskAssessment": "medium",
      "trendPrediction": "待观察",
      "keyPoints": [
        "事件正在发展中",
        "需持续关注官方通报",
        "建议跟踪后续报道"
      ]
    }
  },
  {
    "id": 10,
    "title": "巨力索具被立案调查",
    "category": "社会",
    "source": "今日头条",
    "publishTime": "2026-05-16 05:17:21",
    "heat": 21223557,
    "trend": "rising",
    "sentiment": "negative",
    "riskLevel": "high",
    "isHot": true,
    "isNew": true,
    "excerpt": "",
    "keywords": [
      "巨力索具",
      "被立案调",
      "巨力索具被立"
    ],
    "platform": "toutiao",
    "url": "https://www.toutiao.com/item//",
    "timeline": [
      {
        "time": "05:17",
        "title": "事件发现",
        "desc": "今日头条 监测到该热点",
        "isKey": true
      }
    ],
    "analysis": {
      "sentiment": "negative",
      "sentimentScore": 0.65,
      "riskAssessment": "high",
      "trendPrediction": "待观察",
      "keyPoints": [
        "事件正在发展中",
        "需持续关注官方通报",
        "建议跟踪后续报道"
      ]
    }
  },
  {
    "id": 11,
    "title": "河南驻马店突发火情？谣言",
    "category": "社会",
    "source": "今日头条",
    "publishTime": "2026-05-16 05:17:21",
    "heat": 19203868,
    "trend": "rising",
    "sentiment": "neutral",
    "riskLevel": "medium",
    "isHot": true,
    "isNew": true,
    "excerpt": "",
    "keywords": [
      "河南驻马",
      "店突发火",
      "河南驻马店突"
    ],
    "platform": "toutiao",
    "url": "https://www.toutiao.com/item//",
    "timeline": [
      {
        "time": "05:17",
        "title": "事件发现",
        "desc": "今日头条 监测到该热点",
        "isKey": true
      }
    ],
    "analysis": {
      "sentiment": "neutral",
      "sentimentScore": 0.65,
      "riskAssessment": "medium",
      "trendPrediction": "待观察",
      "keyPoints": [
        "事件正在发展中",
        "需持续关注官方通报",
        "建议跟踪后续报道"
      ]
    }
  },
  {
    "id": 12,
    "title": "薛之谦也被盲道摆拍骗了",
    "category": "社会",
    "source": "今日头条",
    "publishTime": "2026-05-16 05:17:21",
    "heat": 17376379,
    "trend": "rising",
    "sentiment": "neutral",
    "riskLevel": "medium",
    "isHot": true,
    "isNew": true,
    "excerpt": "",
    "keywords": [
      "薛之谦也",
      "被盲道摆",
      "薛之谦也被盲"
    ],
    "platform": "toutiao",
    "url": "https://www.toutiao.com/item//",
    "timeline": [
      {
        "time": "05:17",
        "title": "事件发现",
        "desc": "今日头条 监测到该热点",
        "isKey": true
      }
    ],
    "analysis": {
      "sentiment": "neutral",
      "sentimentScore": 0.65,
      "riskAssessment": "medium",
      "trendPrediction": "待观察",
      "keyPoints": [
        "事件正在发展中",
        "需持续关注官方通报",
        "建议跟踪后续报道"
      ]
    }
  },
  {
    "id": 13,
    "title": "茅台今起涨价",
    "category": "社会",
    "source": "今日头条",
    "publishTime": "2026-05-16 05:17:21",
    "heat": 15722798,
    "trend": "rising",
    "sentiment": "neutral",
    "riskLevel": "medium",
    "isHot": true,
    "isNew": true,
    "excerpt": "",
    "keywords": [
      "茅台今起",
      "茅台今起涨价"
    ],
    "platform": "toutiao",
    "url": "https://www.toutiao.com/item//",
    "timeline": [
      {
        "time": "05:17",
        "title": "事件发现",
        "desc": "今日头条 监测到该热点",
        "isKey": true
      }
    ],
    "analysis": {
      "sentiment": "neutral",
      "sentimentScore": 0.65,
      "riskAssessment": "medium",
      "trendPrediction": "待观察",
      "keyPoints": [
        "事件正在发展中",
        "需持续关注官方通报",
        "建议跟踪后续报道"
      ]
    }
  },
  {
    "id": 14,
    "title": "台湾密室女员工扮“吊死鬼”窒息离世",
    "category": "社会",
    "source": "今日头条",
    "publishTime": "2026-05-16 05:17:21",
    "heat": 14226576,
    "trend": "rising",
    "sentiment": "neutral",
    "riskLevel": "medium",
    "isHot": true,
    "isNew": true,
    "excerpt": "",
    "keywords": [
      "台湾密室",
      "女员工扮",
      "台湾密室女员"
    ],
    "platform": "toutiao",
    "url": "https://www.toutiao.com/item//",
    "timeline": [
      {
        "time": "05:17",
        "title": "事件发现",
        "desc": "今日头条 监测到该热点",
        "isKey": true
      }
    ],
    "analysis": {
      "sentiment": "neutral",
      "sentimentScore": 0.65,
      "riskAssessment": "medium",
      "trendPrediction": "待观察",
      "keyPoints": [
        "事件正在发展中",
        "需持续关注官方通报",
        "建议跟踪后续报道"
      ]
    }
  },
  {
    "id": 15,
    "title": "特朗普离开这一幕中国军人尽显英姿",
    "category": "社会",
    "source": "今日头条",
    "publishTime": "2026-05-16 05:17:21",
    "heat": 12872738,
    "trend": "rising",
    "sentiment": "neutral",
    "riskLevel": "medium",
    "isHot": true,
    "isNew": true,
    "excerpt": "",
    "keywords": [
      "特朗普离",
      "开这一幕",
      "特朗普离开这"
    ],
    "platform": "toutiao",
    "url": "https://www.toutiao.com/item//",
    "timeline": [
      {
        "time": "05:17",
        "title": "事件发现",
        "desc": "今日头条 监测到该热点",
        "isKey": true
      }
    ],
    "analysis": {
      "sentiment": "neutral",
      "sentimentScore": 0.65,
      "riskAssessment": "medium",
      "trendPrediction": "待观察",
      "keyPoints": [
        "事件正在发展中",
        "需持续关注官方通报",
        "建议跟踪后续报道"
      ]
    }
  },
  {
    "id": 16,
    "title": "U17国足3:1逆转沙特",
    "category": "社会",
    "source": "抖音热榜",
    "publishTime": "2026-05-16 05:17:21",
    "heat": 12108470,
    "trend": "rising",
    "sentiment": "neutral",
    "riskLevel": "medium",
    "isHot": true,
    "isNew": true,
    "excerpt": "U17国足3:1逆转沙特...",
    "keywords": [
      "U17国",
      "足3:1",
      "U17国足3"
    ],
    "platform": "douyin",
    "url": "https://www.douyin.com/hot/2500716",
    "timeline": [
      {
        "time": "05:17",
        "title": "事件发现",
        "desc": "抖音热榜 监测到该热点",
        "isKey": true
      }
    ],
    "analysis": {
      "sentiment": "neutral",
      "sentimentScore": 0.65,
      "riskAssessment": "medium",
      "trendPrediction": "待观察",
      "keyPoints": [
        "事件正在发展中",
        "需持续关注官方通报",
        "建议跟踪后续报道"
      ]
    }
  },
  {
    "id": 17,
    "title": "韩红基金会：2025年度收入近7.83亿",
    "category": "经济",
    "source": "今日头条",
    "publishTime": "2026-05-16 05:17:21",
    "heat": 11647735,
    "trend": "rising",
    "sentiment": "neutral",
    "riskLevel": "medium",
    "isHot": true,
    "isNew": true,
    "excerpt": "",
    "keywords": [
      "韩红基金",
      "会：20",
      "韩红基金会："
    ],
    "platform": "toutiao",
    "url": "https://www.toutiao.com/item//",
    "timeline": [
      {
        "time": "05:17",
        "title": "事件发现",
        "desc": "今日头条 监测到该热点",
        "isKey": true
      }
    ],
    "analysis": {
      "sentiment": "neutral",
      "sentimentScore": 0.65,
      "riskAssessment": "medium",
      "trendPrediction": "待观察",
      "keyPoints": [
        "事件正在发展中",
        "需持续关注官方通报",
        "建议跟踪后续报道"
      ]
    }
  },
  {
    "id": 18,
    "title": "美加墨世界杯十大热门球队前瞻",
    "category": "体育",
    "source": "抖音热榜",
    "publishTime": "2026-05-16 05:17:21",
    "heat": 11541413,
    "trend": "rising",
    "sentiment": "neutral",
    "riskLevel": "medium",
    "isHot": true,
    "isNew": true,
    "excerpt": "美加墨世界杯十大热门球队前瞻...",
    "keywords": [
      "美加墨世",
      "界杯十大",
      "美加墨世界杯"
    ],
    "platform": "douyin",
    "url": "https://www.douyin.com/hot/2500692",
    "timeline": [
      {
        "time": "05:17",
        "title": "事件发现",
        "desc": "抖音热榜 监测到该热点",
        "isKey": true
      }
    ],
    "analysis": {
      "sentiment": "neutral",
      "sentimentScore": 0.65,
      "riskAssessment": "medium",
      "trendPrediction": "待观察",
      "keyPoints": [
        "事件正在发展中",
        "需持续关注官方通报",
        "建议跟踪后续报道"
      ]
    }
  },
  {
    "id": 19,
    "title": "中国算力基建开辟海上赛道",
    "category": "社会",
    "source": "抖音热榜",
    "publishTime": "2026-05-16 05:17:21",
    "heat": 11108268,
    "trend": "rising",
    "sentiment": "neutral",
    "riskLevel": "medium",
    "isHot": true,
    "isNew": true,
    "excerpt": "中国算力基建开辟海上赛道...",
    "keywords": [
      "中国算力",
      "基建开辟",
      "中国算力基建"
    ],
    "platform": "douyin",
    "url": "https://www.douyin.com/hot/2500863",
    "timeline": [
      {
        "time": "05:17",
        "title": "事件发现",
        "desc": "抖音热榜 监测到该热点",
        "isKey": true
      }
    ],
    "analysis": {
      "sentiment": "neutral",
      "sentimentScore": 0.65,
      "riskAssessment": "medium",
      "trendPrediction": "待观察",
      "keyPoints": [
        "事件正在发展中",
        "需持续关注官方通报",
        "建议跟踪后续报道"
      ]
    }
  },
  {
    "id": 20,
    "title": "一口气刷完金融入门知识",
    "category": "经济",
    "source": "抖音热榜",
    "publishTime": "2026-05-16 05:17:21",
    "heat": 11084589,
    "trend": "rising",
    "sentiment": "neutral",
    "riskLevel": "medium",
    "isHot": true,
    "isNew": true,
    "excerpt": "一口气刷完金融入门知识...",
    "keywords": [
      "一口气刷",
      "完金融入",
      "一口气刷完金"
    ],
    "platform": "douyin",
    "url": "https://www.douyin.com/hot/2500187",
    "timeline": [
      {
        "time": "05:17",
        "title": "事件发现",
        "desc": "抖音热榜 监测到该热点",
        "isKey": true
      }
    ],
    "analysis": {
      "sentiment": "neutral",
      "sentimentScore": 0.65,
      "riskAssessment": "medium",
      "trendPrediction": "待观察",
      "keyPoints": [
        "事件正在发展中",
        "需持续关注官方通报",
        "建议跟踪后续报道"
      ]
    }
  },
  {
    "id": 21,
    "title": "中方吁有关国家撤回在海外部署核武器",
    "category": "社会",
    "source": "今日头条",
    "publishTime": "2026-05-16 05:17:21",
    "heat": 10539306,
    "trend": "rising",
    "sentiment": "neutral",
    "riskLevel": "medium",
    "isHot": true,
    "isNew": true,
    "excerpt": "",
    "keywords": [
      "中方吁有",
      "关国家撤",
      "中方吁有关国"
    ],
    "platform": "toutiao",
    "url": "https://www.toutiao.com/item//",
    "timeline": [
      {
        "time": "05:17",
        "title": "事件发现",
        "desc": "今日头条 监测到该热点",
        "isKey": true
      }
    ],
    "analysis": {
      "sentiment": "neutral",
      "sentimentScore": 0.65,
      "riskAssessment": "medium",
      "trendPrediction": "待观察",
      "keyPoints": [
        "事件正在发展中",
        "需持续关注官方通报",
        "建议跟踪后续报道"
      ]
    }
  },
  {
    "id": 22,
    "title": "我的初夏充能计划",
    "category": "社会",
    "source": "抖音热榜",
    "publishTime": "2026-05-16 05:17:21",
    "heat": 10510857,
    "trend": "rising",
    "sentiment": "neutral",
    "riskLevel": "medium",
    "isHot": true,
    "isNew": true,
    "excerpt": "我的初夏充能计划...",
    "keywords": [
      "我的初夏",
      "我的初夏充能"
    ],
    "platform": "douyin",
    "url": "https://www.douyin.com/hot/2499979",
    "timeline": [
      {
        "time": "05:17",
        "title": "事件发现",
        "desc": "抖音热榜 监测到该热点",
        "isKey": true
      }
    ],
    "analysis": {
      "sentiment": "neutral",
      "sentimentScore": 0.65,
      "riskAssessment": "medium",
      "trendPrediction": "待观察",
      "keyPoints": [
        "事件正在发展中",
        "需持续关注官方通报",
        "建议跟踪后续报道"
      ]
    }
  },
  {
    "id": 23,
    "title": "不靠建模靠穿搭",
    "category": "时尚",
    "source": "抖音热榜",
    "publishTime": "2026-05-16 05:17:21",
    "heat": 10284520,
    "trend": "rising",
    "sentiment": "neutral",
    "riskLevel": "medium",
    "isHot": true,
    "isNew": true,
    "excerpt": "不靠建模靠穿搭...",
    "keywords": [
      "不靠建模",
      "不靠建模靠穿"
    ],
    "platform": "douyin",
    "url": "https://www.douyin.com/hot/2500478",
    "timeline": [
      {
        "time": "05:17",
        "title": "事件发现",
        "desc": "抖音热榜 监测到该热点",
        "isKey": true
      }
    ],
    "analysis": {
      "sentiment": "neutral",
      "sentimentScore": 0.65,
      "riskAssessment": "medium",
      "trendPrediction": "待观察",
      "keyPoints": [
        "事件正在发展中",
        "需持续关注官方通报",
        "建议跟踪后续报道"
      ]
    }
  },
  {
    "id": 24,
    "title": "摆拍“走盲道被撞”博主账号被禁止关注",
    "category": "社会",
    "source": "今日头条",
    "publishTime": "2026-05-16 05:17:21",
    "heat": 9536359,
    "trend": "rising",
    "sentiment": "neutral",
    "riskLevel": "medium",
    "isHot": true,
    "isNew": true,
    "excerpt": "",
    "keywords": [
      "摆拍“走",
      "盲道被撞",
      "摆拍“走盲道"
    ],
    "platform": "toutiao",
    "url": "https://www.toutiao.com/item//",
    "timeline": [
      {
        "time": "05:17",
        "title": "事件发现",
        "desc": "今日头条 监测到该热点",
        "isKey": true
      }
    ],
    "analysis": {
      "sentiment": "neutral",
      "sentimentScore": 0.65,
      "riskAssessment": "medium",
      "trendPrediction": "待观察",
      "keyPoints": [
        "事件正在发展中",
        "需持续关注官方通报",
        "建议跟踪后续报道"
      ]
    }
  },
  {
    "id": 25,
    "title": "金价银价大跌",
    "category": "社会",
    "source": "抖音热榜",
    "publishTime": "2026-05-16 05:17:21",
    "heat": 9141823,
    "trend": "rising",
    "sentiment": "neutral",
    "riskLevel": "medium",
    "isHot": true,
    "isNew": true,
    "excerpt": "金价银价大跌...",
    "keywords": [
      "金价银价",
      "金价银价大跌"
    ],
    "platform": "douyin",
    "url": "https://www.douyin.com/hot/2500833",
    "timeline": [
      {
        "time": "05:17",
        "title": "事件发现",
        "desc": "抖音热榜 监测到该热点",
        "isKey": true
      }
    ],
    "analysis": {
      "sentiment": "neutral",
      "sentimentScore": 0.65,
      "riskAssessment": "medium",
      "trendPrediction": "待观察",
      "keyPoints": [
        "事件正在发展中",
        "需持续关注官方通报",
        "建议跟踪后续报道"
      ]
    }
  },
  {
    "id": 26,
    "title": "岁月为我大浪淘沙",
    "category": "社会",
    "source": "抖音热榜",
    "publishTime": "2026-05-16 05:17:21",
    "heat": 8711606,
    "trend": "rising",
    "sentiment": "neutral",
    "riskLevel": "medium",
    "isHot": true,
    "isNew": true,
    "excerpt": "岁月为我大浪淘沙...",
    "keywords": [
      "岁月为我",
      "岁月为我大浪"
    ],
    "platform": "douyin",
    "url": "https://www.douyin.com/hot/2500213",
    "timeline": [
      {
        "time": "05:17",
        "title": "事件发现",
        "desc": "抖音热榜 监测到该热点",
        "isKey": true
      }
    ],
    "analysis": {
      "sentiment": "neutral",
      "sentimentScore": 0.65,
      "riskAssessment": "medium",
      "trendPrediction": "待观察",
      "keyPoints": [
        "事件正在发展中",
        "需持续关注官方通报",
        "建议跟踪后续报道"
      ]
    }
  },
  {
    "id": 27,
    "title": "BLG战胜TES",
    "category": "社会",
    "source": "抖音热榜",
    "publishTime": "2026-05-16 05:17:21",
    "heat": 8671864,
    "trend": "rising",
    "sentiment": "neutral",
    "riskLevel": "medium",
    "isHot": true,
    "isNew": true,
    "excerpt": "BLG战胜TES...",
    "keywords": [
      "BLG战",
      "BLG战胜T"
    ],
    "platform": "douyin",
    "url": "https://www.douyin.com/hot/2500704",
    "timeline": [
      {
        "time": "05:17",
        "title": "事件发现",
        "desc": "抖音热榜 监测到该热点",
        "isKey": true
      }
    ],
    "analysis": {
      "sentiment": "neutral",
      "sentimentScore": 0.65,
      "riskAssessment": "medium",
      "trendPrediction": "待观察",
      "keyPoints": [
        "事件正在发展中",
        "需持续关注官方通报",
        "建议跟踪后续报道"
      ]
    }
  },
  {
    "id": 28,
    "title": "中方将买200架波音飞机？外交部回应",
    "category": "国际",
    "source": "今日头条",
    "publishTime": "2026-05-16 05:17:21",
    "heat": 8628854,
    "trend": "rising",
    "sentiment": "neutral",
    "riskLevel": "medium",
    "isHot": true,
    "isNew": true,
    "excerpt": "",
    "keywords": [
      "中方将买",
      "200架",
      "中方将买20"
    ],
    "platform": "toutiao",
    "url": "https://www.toutiao.com/item//",
    "timeline": [
      {
        "time": "05:17",
        "title": "事件发现",
        "desc": "今日头条 监测到该热点",
        "isKey": true
      }
    ],
    "analysis": {
      "sentiment": "neutral",
      "sentimentScore": 0.65,
      "riskAssessment": "medium",
      "trendPrediction": "待观察",
      "keyPoints": [
        "事件正在发展中",
        "需持续关注官方通报",
        "建议跟踪后续报道"
      ]
    }
  },
  {
    "id": 29,
    "title": "樊振东备战欧冠半决赛",
    "category": "社会",
    "source": "抖音热榜",
    "publishTime": "2026-05-16 05:17:21",
    "heat": 7832263,
    "trend": "stable",
    "sentiment": "neutral",
    "riskLevel": "low",
    "isHot": true,
    "isNew": true,
    "excerpt": "樊振东备战欧冠半决赛...",
    "keywords": [
      "樊振东备",
      "战欧冠半",
      "樊振东备战欧"
    ],
    "platform": "douyin",
    "url": "https://www.douyin.com/hot/2500942",
    "timeline": [
      {
        "time": "05:17",
        "title": "事件发现",
        "desc": "抖音热榜 监测到该热点",
        "isKey": true
      }
    ],
    "analysis": {
      "sentiment": "neutral",
      "sentimentScore": 0.65,
      "riskAssessment": "low",
      "trendPrediction": "待观察",
      "keyPoints": [
        "事件正在发展中",
        "需持续关注官方通报",
        "建议跟踪后续报道"
      ]
    }
  },
  {
    "id": 30,
    "title": "骑士94:115不敌活塞",
    "category": "社会",
    "source": "抖音热榜",
    "publishTime": "2026-05-16 05:17:21",
    "heat": 7815863,
    "trend": "stable",
    "sentiment": "neutral",
    "riskLevel": "low",
    "isHot": true,
    "isNew": true,
    "excerpt": "骑士94:115不敌活塞...",
    "keywords": [
      "骑士94",
      ":115",
      "骑士94:1"
    ],
    "platform": "douyin",
    "url": "https://www.douyin.com/hot/2500869",
    "timeline": [
      {
        "time": "05:17",
        "title": "事件发现",
        "desc": "抖音热榜 监测到该热点",
        "isKey": true
      }
    ],
    "analysis": {
      "sentiment": "neutral",
      "sentimentScore": 0.65,
      "riskAssessment": "low",
      "trendPrediction": "待观察",
      "keyPoints": [
        "事件正在发展中",
        "需持续关注官方通报",
        "建议跟踪后续报道"
      ]
    }
  },
  {
    "id": 31,
    "title": "特朗普说随访美国商人是自己想来的",
    "category": "国际",
    "source": "今日头条",
    "publishTime": "2026-05-16 05:17:21",
    "heat": 7807710,
    "trend": "stable",
    "sentiment": "neutral",
    "riskLevel": "low",
    "isHot": true,
    "isNew": true,
    "excerpt": "",
    "keywords": [
      "特朗普说",
      "随访美国",
      "特朗普说随访"
    ],
    "platform": "toutiao",
    "url": "https://www.toutiao.com/item//",
    "timeline": [
      {
        "time": "05:17",
        "title": "事件发现",
        "desc": "今日头条 监测到该热点",
        "isKey": true
      }
    ],
    "analysis": {
      "sentiment": "neutral",
      "sentimentScore": 0.65,
      "riskAssessment": "low",
      "trendPrediction": "待观察",
      "keyPoints": [
        "事件正在发展中",
        "需持续关注官方通报",
        "建议跟踪后续报道"
      ]
    }
  },
  {
    "id": 32,
    "title": "不倒翁挑战",
    "category": "社会",
    "source": "抖音热榜",
    "publishTime": "2026-05-16 05:17:21",
    "heat": 7806317,
    "trend": "stable",
    "sentiment": "neutral",
    "riskLevel": "low",
    "isHot": true,
    "isNew": true,
    "excerpt": "不倒翁挑战...",
    "keywords": [
      "不倒翁挑",
      "不倒翁挑战"
    ],
    "platform": "douyin",
    "url": "https://www.douyin.com/hot/2500211",
    "timeline": [
      {
        "time": "05:17",
        "title": "事件发现",
        "desc": "抖音热榜 监测到该热点",
        "isKey": true
      }
    ],
    "analysis": {
      "sentiment": "neutral",
      "sentimentScore": 0.65,
      "riskAssessment": "low",
      "trendPrediction": "待观察",
      "keyPoints": [
        "事件正在发展中",
        "需持续关注官方通报",
        "建议跟踪后续报道"
      ]
    }
  },
  {
    "id": 33,
    "title": "人形机器人“上岗”快递分拣员",
    "category": "社会",
    "source": "抖音热榜",
    "publishTime": "2026-05-16 05:17:21",
    "heat": 7782668,
    "trend": "stable",
    "sentiment": "neutral",
    "riskLevel": "low",
    "isHot": true,
    "isNew": true,
    "excerpt": "人形机器人“上岗”快递分拣员...",
    "keywords": [
      "人形机器",
      "人“上岗",
      "人形机器人“"
    ],
    "platform": "douyin",
    "url": "https://www.douyin.com/hot/2499915",
    "timeline": [
      {
        "time": "05:17",
        "title": "事件发现",
        "desc": "抖音热榜 监测到该热点",
        "isKey": true
      }
    ],
    "analysis": {
      "sentiment": "neutral",
      "sentimentScore": 0.65,
      "riskAssessment": "low",
      "trendPrediction": "待观察",
      "keyPoints": [
        "事件正在发展中",
        "需持续关注官方通报",
        "建议跟踪后续报道"
      ]
    }
  },
  {
    "id": 34,
    "title": "蒙超开幕式豪迈歌声点燃赛场",
    "category": "社会",
    "source": "抖音热榜",
    "publishTime": "2026-05-16 05:17:21",
    "heat": 7769925,
    "trend": "stable",
    "sentiment": "neutral",
    "riskLevel": "low",
    "isHot": true,
    "isNew": true,
    "excerpt": "蒙超开幕式豪迈歌声点燃赛场...",
    "keywords": [
      "蒙超开幕",
      "式豪迈歌",
      "蒙超开幕式豪"
    ],
    "platform": "douyin",
    "url": "https://www.douyin.com/hot/2500599",
    "timeline": [
      {
        "time": "05:17",
        "title": "事件发现",
        "desc": "抖音热榜 监测到该热点",
        "isKey": true
      }
    ],
    "analysis": {
      "sentiment": "neutral",
      "sentimentScore": 0.65,
      "riskAssessment": "low",
      "trendPrediction": "待观察",
      "keyPoints": [
        "事件正在发展中",
        "需持续关注官方通报",
        "建议跟踪后续报道"
      ]
    }
  },
  {
    "id": 35,
    "title": "中超上海海港2:2浙江队",
    "category": "社会",
    "source": "抖音热榜",
    "publishTime": "2026-05-16 05:17:21",
    "heat": 7767562,
    "trend": "stable",
    "sentiment": "neutral",
    "riskLevel": "low",
    "isHot": true,
    "isNew": true,
    "excerpt": "中超上海海港2:2浙江队...",
    "keywords": [
      "中超上海",
      "海港2:",
      "中超上海海港"
    ],
    "platform": "douyin",
    "url": "https://www.douyin.com/hot/2500663",
    "timeline": [
      {
        "time": "05:17",
        "title": "事件发现",
        "desc": "抖音热榜 监测到该热点",
        "isKey": true
      }
    ],
    "analysis": {
      "sentiment": "neutral",
      "sentimentScore": 0.65,
      "riskAssessment": "low",
      "trendPrediction": "待观察",
      "keyPoints": [
        "事件正在发展中",
        "需持续关注官方通报",
        "建议跟踪后续报道"
      ]
    }
  },
  {
    "id": 36,
    "title": "乘风师姐帮唱小考",
    "category": "社会",
    "source": "抖音热榜",
    "publishTime": "2026-05-16 05:17:21",
    "heat": 7763219,
    "trend": "stable",
    "sentiment": "neutral",
    "riskLevel": "low",
    "isHot": true,
    "isNew": true,
    "excerpt": "乘风师姐帮唱小考...",
    "keywords": [
      "乘风师姐",
      "乘风师姐帮唱"
    ],
    "platform": "douyin",
    "url": "https://www.douyin.com/hot/2500121",
    "timeline": [
      {
        "time": "05:17",
        "title": "事件发现",
        "desc": "抖音热榜 监测到该热点",
        "isKey": true
      }
    ],
    "analysis": {
      "sentiment": "neutral",
      "sentimentScore": 0.65,
      "riskAssessment": "low",
      "trendPrediction": "待观察",
      "keyPoints": [
        "事件正在发展中",
        "需持续关注官方通报",
        "建议跟踪后续报道"
      ]
    }
  },
  {
    "id": 37,
    "title": "七彩阳光手指操来了",
    "category": "社会",
    "source": "抖音热榜",
    "publishTime": "2026-05-16 05:17:21",
    "heat": 7751402,
    "trend": "stable",
    "sentiment": "neutral",
    "riskLevel": "low",
    "isHot": true,
    "isNew": true,
    "excerpt": "七彩阳光手指操来了...",
    "keywords": [
      "七彩阳光",
      "手指操来",
      "七彩阳光手指"
    ],
    "platform": "douyin",
    "url": "https://www.douyin.com/hot/2499416",
    "timeline": [
      {
        "time": "05:17",
        "title": "事件发现",
        "desc": "抖音热榜 监测到该热点",
        "isKey": true
      }
    ],
    "analysis": {
      "sentiment": "neutral",
      "sentimentScore": 0.65,
      "riskAssessment": "low",
      "trendPrediction": "待观察",
      "keyPoints": [
        "事件正在发展中",
        "需持续关注官方通报",
        "建议跟踪后续报道"
      ]
    }
  },
  {
    "id": 38,
    "title": "我发现灰太狼的城堡了",
    "category": "社会",
    "source": "抖音热榜",
    "publishTime": "2026-05-16 05:17:21",
    "heat": 7750436,
    "trend": "stable",
    "sentiment": "neutral",
    "riskLevel": "low",
    "isHot": true,
    "isNew": true,
    "excerpt": "我发现灰太狼的城堡了...",
    "keywords": [
      "我发现灰",
      "太狼的城",
      "我发现灰太狼"
    ],
    "platform": "douyin",
    "url": "https://www.douyin.com/hot/2500852",
    "timeline": [
      {
        "time": "05:17",
        "title": "事件发现",
        "desc": "抖音热榜 监测到该热点",
        "isKey": true
      }
    ],
    "analysis": {
      "sentiment": "neutral",
      "sentimentScore": 0.65,
      "riskAssessment": "low",
      "trendPrediction": "待观察",
      "keyPoints": [
        "事件正在发展中",
        "需持续关注官方通报",
        "建议跟踪后续报道"
      ]
    }
  },
  {
    "id": 39,
    "title": "数节拍手势挑战",
    "category": "社会",
    "source": "抖音热榜",
    "publishTime": "2026-05-16 05:17:21",
    "heat": 7747551,
    "trend": "stable",
    "sentiment": "neutral",
    "riskLevel": "low",
    "isHot": true,
    "isNew": true,
    "excerpt": "数节拍手势挑战...",
    "keywords": [
      "数节拍手",
      "数节拍手势挑"
    ],
    "platform": "douyin",
    "url": "https://www.douyin.com/hot/2498702",
    "timeline": [
      {
        "time": "05:17",
        "title": "事件发现",
        "desc": "抖音热榜 监测到该热点",
        "isKey": true
      }
    ],
    "analysis": {
      "sentiment": "neutral",
      "sentimentScore": 0.65,
      "riskAssessment": "low",
      "trendPrediction": "待观察",
      "keyPoints": [
        "事件正在发展中",
        "需持续关注官方通报",
        "建议跟踪后续报道"
      ]
    }
  },
  {
    "id": 40,
    "title": "蛋仔版何必心存侥幸",
    "category": "社会",
    "source": "抖音热榜",
    "publishTime": "2026-05-16 05:17:21",
    "heat": 7741370,
    "trend": "stable",
    "sentiment": "neutral",
    "riskLevel": "low",
    "isHot": true,
    "isNew": true,
    "excerpt": "蛋仔版何必心存侥幸...",
    "keywords": [
      "蛋仔版何",
      "必心存侥",
      "蛋仔版何必心"
    ],
    "platform": "douyin",
    "url": "https://www.douyin.com/hot/2500275",
    "timeline": [
      {
        "time": "05:17",
        "title": "事件发现",
        "desc": "抖音热榜 监测到该热点",
        "isKey": true
      }
    ],
    "analysis": {
      "sentiment": "neutral",
      "sentimentScore": 0.65,
      "riskAssessment": "low",
      "trendPrediction": "待观察",
      "keyPoints": [
        "事件正在发展中",
        "需持续关注官方通报",
        "建议跟踪后续报道"
      ]
    }
  },
  {
    "id": 41,
    "title": "给阿嬷的情书",
    "category": "社会",
    "source": "豆瓣电影",
    "publishTime": "2026-05-16 05:17:21",
    "heat": 90000,
    "trend": "stable",
    "sentiment": "neutral",
    "riskLevel": "low",
    "isHot": false,
    "isNew": true,
    "excerpt": "",
    "keywords": [
      "给阿嬷的",
      "给阿嬷的情书"
    ],
    "platform": "douban",
    "url": "https://movie.douban.com/subject/37116446/",
    "timeline": [
      {
        "time": "05:17",
        "title": "事件发现",
        "desc": "豆瓣电影 监测到该热点",
        "isKey": true
      }
    ],
    "analysis": {
      "sentiment": "neutral",
      "sentimentScore": 0.65,
      "riskAssessment": "low",
      "trendPrediction": "待观察",
      "keyPoints": [
        "事件正在发展中",
        "需持续关注官方通报",
        "建议跟踪后续报道"
      ]
    }
  },
  {
    "id": 42,
    "title": "世界的主人",
    "category": "社会",
    "source": "豆瓣电影",
    "publishTime": "2026-05-16 05:17:21",
    "heat": 90000,
    "trend": "stable",
    "sentiment": "neutral",
    "riskLevel": "low",
    "isHot": false,
    "isNew": true,
    "excerpt": "",
    "keywords": [
      "世界的主",
      "世界的主人"
    ],
    "platform": "douban",
    "url": "https://movie.douban.com/subject/37116612/",
    "timeline": [
      {
        "time": "05:17",
        "title": "事件发现",
        "desc": "豆瓣电影 监测到该热点",
        "isKey": true
      }
    ],
    "analysis": {
      "sentiment": "neutral",
      "sentimentScore": 0.65,
      "riskAssessment": "low",
      "trendPrediction": "待观察",
      "keyPoints": [
        "事件正在发展中",
        "需持续关注官方通报",
        "建议跟踪后续报道"
      ]
    }
  },
  {
    "id": 43,
    "title": "我，许可",
    "category": "社会",
    "source": "豆瓣电影",
    "publishTime": "2026-05-16 05:17:21",
    "heat": 80000,
    "trend": "stable",
    "sentiment": "neutral",
    "riskLevel": "low",
    "isHot": false,
    "isNew": true,
    "excerpt": "",
    "keywords": [
      "我"
    ],
    "platform": "douban",
    "url": "https://movie.douban.com/subject/37332784/",
    "timeline": [
      {
        "time": "05:17",
        "title": "事件发现",
        "desc": "豆瓣电影 监测到该热点",
        "isKey": true
      }
    ],
    "analysis": {
      "sentiment": "neutral",
      "sentimentScore": 0.65,
      "riskAssessment": "low",
      "trendPrediction": "待观察",
      "keyPoints": [
        "事件正在发展中",
        "需持续关注官方通报",
        "建议跟踪后续报道"
      ]
    }
  },
  {
    "id": 44,
    "title": "再见，朱莉娅",
    "category": "社会",
    "source": "豆瓣电影",
    "publishTime": "2026-05-16 05:17:21",
    "heat": 80000,
    "trend": "stable",
    "sentiment": "neutral",
    "riskLevel": "low",
    "isHot": false,
    "isNew": true,
    "excerpt": "",
    "keywords": [
      "再见，朱",
      "再见"
    ],
    "platform": "douban",
    "url": "https://movie.douban.com/subject/36070920/",
    "timeline": [
      {
        "time": "05:17",
        "title": "事件发现",
        "desc": "豆瓣电影 监测到该热点",
        "isKey": true
      }
    ],
    "analysis": {
      "sentiment": "neutral",
      "sentimentScore": 0.65,
      "riskAssessment": "low",
      "trendPrediction": "待观察",
      "keyPoints": [
        "事件正在发展中",
        "需持续关注官方通报",
        "建议跟踪后续报道"
      ]
    }
  },
  {
    "id": 45,
    "title": "纵横四海",
    "category": "社会",
    "source": "豆瓣电影",
    "publishTime": "2026-05-16 05:17:21",
    "heat": 80000,
    "trend": "stable",
    "sentiment": "neutral",
    "riskLevel": "low",
    "isHot": false,
    "isNew": true,
    "excerpt": "",
    "keywords": [
      "纵横四海"
    ],
    "platform": "douban",
    "url": "https://movie.douban.com/subject/1295409/",
    "timeline": [
      {
        "time": "05:17",
        "title": "事件发现",
        "desc": "豆瓣电影 监测到该热点",
        "isKey": true
      }
    ],
    "analysis": {
      "sentiment": "neutral",
      "sentimentScore": 0.65,
      "riskAssessment": "low",
      "trendPrediction": "待观察",
      "keyPoints": [
        "事件正在发展中",
        "需持续关注官方通报",
        "建议跟踪后续报道"
      ]
    }
  },
  {
    "id": 46,
    "title": "大白鲨",
    "category": "社会",
    "source": "豆瓣电影",
    "publishTime": "2026-05-16 05:17:21",
    "heat": 70000,
    "trend": "stable",
    "sentiment": "neutral",
    "riskLevel": "low",
    "isHot": false,
    "isNew": true,
    "excerpt": "",
    "keywords": [
      "大白鲨"
    ],
    "platform": "douban",
    "url": "https://movie.douban.com/subject/1294941/",
    "timeline": [
      {
        "time": "05:17",
        "title": "事件发现",
        "desc": "豆瓣电影 监测到该热点",
        "isKey": true
      }
    ],
    "analysis": {
      "sentiment": "neutral",
      "sentimentScore": 0.65,
      "riskAssessment": "low",
      "trendPrediction": "待观察",
      "keyPoints": [
        "事件正在发展中",
        "需持续关注官方通报",
        "建议跟踪后续报道"
      ]
    }
  },
  {
    "id": 47,
    "title": "消失的人",
    "category": "社会",
    "source": "豆瓣电影",
    "publishTime": "2026-05-16 05:17:21",
    "heat": 70000,
    "trend": "stable",
    "sentiment": "neutral",
    "riskLevel": "low",
    "isHot": false,
    "isNew": true,
    "excerpt": "",
    "keywords": [
      "消失的人"
    ],
    "platform": "douban",
    "url": "https://movie.douban.com/subject/36965301/",
    "timeline": [
      {
        "time": "05:17",
        "title": "事件发现",
        "desc": "豆瓣电影 监测到该热点",
        "isKey": true
      }
    ],
    "analysis": {
      "sentiment": "neutral",
      "sentimentScore": 0.65,
      "riskAssessment": "low",
      "trendPrediction": "待观察",
      "keyPoints": [
        "事件正在发展中",
        "需持续关注官方通报",
        "建议跟踪后续报道"
      ]
    }
  },
  {
    "id": 48,
    "title": "寒战1994",
    "category": "社会",
    "source": "豆瓣电影",
    "publishTime": "2026-05-16 05:17:21",
    "heat": 70000,
    "trend": "stable",
    "sentiment": "neutral",
    "riskLevel": "low",
    "isHot": false,
    "isNew": true,
    "excerpt": "",
    "keywords": [
      "寒战19",
      "寒战1994"
    ],
    "platform": "douban",
    "url": "https://movie.douban.com/subject/36857924/",
    "timeline": [
      {
        "time": "05:17",
        "title": "事件发现",
        "desc": "豆瓣电影 监测到该热点",
        "isKey": true
      }
    ],
    "analysis": {
      "sentiment": "neutral",
      "sentimentScore": 0.65,
      "riskAssessment": "low",
      "trendPrediction": "待观察",
      "keyPoints": [
        "事件正在发展中",
        "需持续关注官方通报",
        "建议跟踪后续报道"
      ]
    }
  },
  {
    "id": 49,
    "title": "绵羊侦探团",
    "category": "社会",
    "source": "豆瓣电影",
    "publishTime": "2026-05-16 05:17:21",
    "heat": 0,
    "trend": "stable",
    "sentiment": "neutral",
    "riskLevel": "low",
    "isHot": false,
    "isNew": true,
    "excerpt": "",
    "keywords": [
      "绵羊侦探",
      "绵羊侦探团"
    ],
    "platform": "douban",
    "url": "https://movie.douban.com/subject/36918069/",
    "timeline": [
      {
        "time": "05:17",
        "title": "事件发现",
        "desc": "豆瓣电影 监测到该热点",
        "isKey": true
      }
    ],
    "analysis": {
      "sentiment": "neutral",
      "sentimentScore": 0.65,
      "riskAssessment": "low",
      "trendPrediction": "待观察",
      "keyPoints": [
        "事件正在发展中",
        "需持续关注官方通报",
        "建议跟踪后续报道"
      ]
    }
  },
  {
    "id": 50,
    "title": "一个男人和一个女人",
    "category": "社会",
    "source": "豆瓣电影",
    "publishTime": "2026-05-16 05:17:21",
    "heat": 0,
    "trend": "stable",
    "sentiment": "neutral",
    "riskLevel": "low",
    "isHot": false,
    "isNew": true,
    "excerpt": "",
    "keywords": [
      "一个男人",
      "和一个女",
      "一个男人和一"
    ],
    "platform": "douban",
    "url": "https://movie.douban.com/subject/36311696/",
    "timeline": [
      {
        "time": "05:17",
        "title": "事件发现",
        "desc": "豆瓣电影 监测到该热点",
        "isKey": true
      }
    ],
    "analysis": {
      "sentiment": "neutral",
      "sentimentScore": 0.65,
      "riskAssessment": "low",
      "trendPrediction": "待观察",
      "keyPoints": [
        "事件正在发展中",
        "需持续关注官方通报",
        "建议跟踪后续报道"
      ]
    }
  }
]